{
	"idle" : "Regola l'auricolare usando le cinghie sui lati e in alto fino a quando non ti senti a tuo agio e puoi vedere questo testo correttamente. \n Quando sei pronto, guarda il pulsante qui sotto per iniziare l'esperienza.",
    "waitForOther" : "Per favore aspetta un momento per l'altro partecipante ...",
	"otherIsGone" : "Woops ... \n Sembra che il tuo collega se ne sia andato! \n Grazie per la tua partecipazione!",
	"instructions" : "Per favore, ricorda... \n \n 1. Muoviti molto lentamente \n 2. Sincronizza i tuoi movimenti \n 3. Seguiti",
	"finished" : "Ci auguriamo che la tua esperienza ti sia piaciuta. \n Grazie!",
	"systemFailure" : "Si è verificato un errore con il sistema. Rimuovi il casco",
	"waitingForSerial" : "Waiting for serial ..."
}